hole_filling_liepa/__init__.py
hole_filling_liepa/core.cp39-win_amd64.pyd
hole_filling_liepa/native.py
hole_filling_liepa/utils.py
hole_filling_liepa-0.0.2.dist-info/METADATA
hole_filling_liepa-0.0.2.dist-info/WHEEL
hole_filling_liepa-0.0.2.dist-info/top_level.txt
hole_filling_liepa-0.0.2.dist-info/RECORD
